devpi_json_info/__init__.py
devpi_json_info/devpi_json_info.py
devpi_json_info-0.1.3.dist-info/LICENSE
devpi_json_info-0.1.3.dist-info/METADATA
devpi_json_info-0.1.3.dist-info/WHEEL
devpi_json_info-0.1.3.dist-info/entry_points.txt
devpi_json_info-0.1.3.dist-info/top_level.txt
devpi_json_info-0.1.3.dist-info/RECORD
