Metadata-Version: 2.1
Name: devpi-json-info
Version: 0.1.3
Summary: devpi-server plugin
Home-page: https://github.com/awachtler/devpi-json-info
Author-email: axel@uracoli.de
License: MIT
Platform: UNKNOWN
Requires-Dist: devpi-server
